icdutil/__init__.py
icdutil/addrmap.py
icdutil/addrrange.py
icdutil/num.py
icdutil/slices.py
icdutil-1.0.0.dist-info/LICENSE
icdutil-1.0.0.dist-info/METADATA
icdutil-1.0.0.dist-info/WHEEL
icdutil-1.0.0.dist-info/RECORD
