Metadata-Version: 2.1
Name: icdutil
Version: 1.0.0
Summary: IC Design Utilities
License: MIT
Requires-Python: >=3.7.2,<4.0.0
Classifier: License :: OSI Approved :: MIT License
Classifier: Operating System :: OS Independent
Classifier: Programming Language :: Python :: 3
Classifier: Programming Language :: Python :: 3.8
Classifier: Programming Language :: Python :: 3.9
Classifier: Programming Language :: Python :: 3.10
Classifier: Programming Language :: Python :: 3.11
Classifier: Programming Language :: Python :: 3.12
Requires-Dist: attrs (>=23.1.0,<24.0.0)
Requires-Dist: humannum (>=1.0.0,<2.0.0)
Requires-Dist: mementos (>=1.3.1,<2.0.0)
Requires-Dist: tabulate (>=0.9.0,<0.10.0)
Requires-Dist: types-tabulate (>=0.9.0,<0.10.0)
